public_drive_urls
