Metadata-Version: 1.0
Name: public-drive-urls
Version: 0.0.4
Summary: Find Google Drive download URLs from a file's sharing URL
Home-page: https://github.com/bepetersn/public-drive-urls/
Author: Brian Peterson
Author-email: bepetersn@gmail.com
License: MIT
Platform: UNKNOWN
